epa_syllabifier/__init__.py
epa_syllabifier/syllabicator.py
epa_syllabifier-0.3.0.dist-info/METADATA
epa_syllabifier-0.3.0.dist-info/WHEEL
epa_syllabifier-0.3.0.dist-info/licenses/LICENSE
epa_syllabifier-0.3.0.dist-info/RECORD
