Metadata-Version: 2.4
Name: epa_syllabifier
Version: 0.3.0
Summary: Automatic syllabification module for Spanish words
Project-URL: Homepage, https://github.com/andalugeeks/epa-syllabifier
Project-URL: Bug Tracker, https://github.com/andalugeeks/epa-syllabifier/issues
Project-URL: Repository, https://github.com/andalugeeks/epa-syllabifier.git
Author: Andalugeeks Team
License-Expression: MIT
License-File: LICENSE
Keywords: linguistics,nlp,spanish,syllabification,text-processing
Classifier: Development Status :: 4 - Beta
Classifier: Intended Audience :: Developers
Classifier: Intended Audience :: Science/Research
Classifier: License :: OSI Approved :: MIT License
Classifier: Operating System :: OS Independent
Classifier: Programming Language :: Python :: 3
Classifier: Programming Language :: Python :: 3.8
Classifier: Programming Language :: Python :: 3.9
Classifier: Programming Language :: Python :: 3.10
Classifier: Programming Language :: Python :: 3.11
Classifier: Programming Language :: Python :: 3.12
Classifier: Topic :: Scientific/Engineering :: Artificial Intelligence
Classifier: Topic :: Text Processing :: Linguistic
Requires-Python: >=3.8
Provides-Extra: dev
Requires-Dist: black; extra == 'dev'
Requires-Dist: commitizen>=3.0.0; extra == 'dev'
Requires-Dist: ipdb; extra == 'dev'
Requires-Dist: pytest-cov>=4.0.0; extra == 'dev'
Requires-Dist: pytest>=7.0.0; extra == 'dev'
